birdisle-0.2.2.dist-info/WHEEL
birdisle-0.2.2.dist-info/top_level.txt
birdisle-0.2.2.dist-info/COPYING
birdisle-0.2.2.dist-info/RECORD
birdisle-0.2.2.dist-info/METADATA
birdisle/redis.py
birdisle/aioredis.py
birdisle/_version.py
birdisle/_birdisle.pypy38-pp73-x86-linux-gnu.so
birdisle/__init__.py
birdisle/.libs/libbirdisle.so.1
