Metadata-Version: 2.1
Name: birdisle
Version: 0.2.2
Summary: Python bindings for birdisle
Home-page: https://github.com/bmerry/birdisle-py
Author: Bruce Merry
Author-email: bmerry@gmail.com
License: BSD
Classifier: Development Status :: 3 - Alpha
Classifier: Intended Audience :: Developers
Classifier: License :: OSI Approved :: BSD License
Classifier: Operating System :: POSIX :: Linux
Classifier: Programming Language :: Python :: 3
Classifier: Programming Language :: Python :: 3.6
Classifier: Programming Language :: Python :: 3.7
Classifier: Programming Language :: Python :: 3.8
Classifier: Programming Language :: Python :: 3.9
Classifier: Programming Language :: Python :: 3.10
Classifier: Programming Language :: Python :: 3.11
Classifier: Topic :: Database
Classifier: Topic :: Software Development :: Testing
Requires-Python: >=3.6
Provides-Extra: redis
Provides-Extra: aioredis
Provides-Extra: test
License-File: COPYING
